[
    {
        "material": {
            "ambient": [
                0.1,
                0.1,
                0.1
            ],
            "diffuse": [
                0.49999985098838806,
                0.0,
                0.5000000596046448
            ],
            "specular": [
                0.5999999940395355,
                0.5999999940395355,
                0.5999999940395355
            ],
            "n": 5
        },
        "vertices": [
            [
                0.7474287450313568,
                0.0014972686767578125,
                1.3964146971702576
            ],
            [
                0.5699993148446083,
                0.0015651285648345947,
                1.0772671103477478
            ],
            [
                0.25257183611392975,
                0.0014969706535339355,
                0.4724987931549549
            ],
            [
                0.43000126630067825,
                0.001565009355545044,
                0.791646420955658
            ],
            [
                0.4999997076093905,
                1.0,
                0.9344567060470581
            ]
        ],
        "triangles": [
            [
                0,
                4,
                1
            ],
            [
                1,
                4,
                2
            ],
            [
                2,
                4,
                3
            ],
            [
                3,
                4,
                0
            ],
            [
                2,
                3,
                0
            ],
            [
                2,
                0,
                1
            ]
        ]
    }
]