[
    {
        "material": {
            "ambient": [
                0.1,
                0.1,
                0.1
            ],
            "diffuse": [
                1.0,
                0.0,
                0.0
            ],
            "specular": [
                0.5999999940395355,
                0.5999999940395355,
                0.5999999940395355
            ],
            "n": 5
        },
        "vertices": [
            [
                0.9911159873008728,
                0.001497417688369751,
                1.1467158198356628
            ],
            [
                0.42635563015937805,
                0.0015650391578674316,
                1.316765010356903
            ],
            [
                0.008884608745574951,
                0.001496821641921997,
                0.7221976965665817
            ],
            [
                0.5736449658870697,
                0.001565098762512207,
                0.5521485097706318
            ],
            [
                0.4999996999668781,
                1.0,
                0.9344567358493805
            ]
        ],
        "triangles": [
            [
                0,
                4,
                1
            ],
            [
                1,
                4,
                2
            ],
            [
                2,
                4,
                3
            ],
            [
                3,
                4,
                0
            ],
            [
                2,
                3,
                0
            ],
            [
                2,
                0,
                1
            ]
        ]
    }
]